ghvault/__init__.py
ghvault/api.py
ghvault/cli.py
ghvault-1.0.0.dist-info/METADATA
ghvault-1.0.0.dist-info/WHEEL
ghvault-1.0.0.dist-info/entry_points.txt
ghvault-1.0.0.dist-info/RECORD
