Metadata-Version: 2.4
Name: ghvault
Version: 1.0.0
Summary: GitHub Environment Secrets Management Tool - Automate uploading secrets from .env files to GitHub environments
Requires-Python: >=3.10
Requires-Dist: click>=8.2.1
Requires-Dist: httpx>=0.28.1
Requires-Dist: isort>=6.0.1
Requires-Dist: pynacl>=1.5.0
Requires-Dist: pytest>=8.4.1
Requires-Dist: tqdm>=4.67.1
Requires-Dist: typer>=0.16.1
Provides-Extra: dev
Requires-Dist: black>=23.0.0; extra == 'dev'
Requires-Dist: flake8>=6.0.0; extra == 'dev'
Requires-Dist: isort>=5.12.0; extra == 'dev'
Requires-Dist: mypy>=1.0.0; extra == 'dev'
Requires-Dist: pre-commit>=3.0.0; extra == 'dev'
Provides-Extra: test
Requires-Dist: coverage>=7.0.0; extra == 'test'
Requires-Dist: pytest-asyncio>=0.21.0; extra == 'test'
Requires-Dist: pytest-cov>=4.0.0; extra == 'test'
Requires-Dist: pytest-mock>=3.10.0; extra == 'test'
Requires-Dist: pytest>=7.0.0; extra == 'test'
